Metadata-Version: 1.0
Name: aditya-distribution
Version: 0.1
Summary: Gaussian Distributions
Home-page: UNKNOWN
Author: Aditya Khadke
Author-email: Aditya.Khadke04@gmail.com
License: UNKNOWN
Platform: UNKNOWN
